README.md
setup.py
ads_bluebook.egg-info/PKG-INFO
ads_bluebook.egg-info/SOURCES.txt
ads_bluebook.egg-info/dependency_links.txt
ads_bluebook.egg-info/top_level.txt
bluebook/__init__.py
bluebook/launch_schedule.py
bluebook/repository.py
bluebook/tle.py
bluebook/validate.py
test/test_launch_schedule.py
test/test_tle_calculations.py