Metadata-Version: 1.0
Name: ads-bluebook
Version: 0.1.15
Summary: The ADS Satellite BlueBook, which does various kinds of webscraping, ExcelSheet parsing, and api calls to collect itself into a central database.
Home-page: UNKNOWN
Author: UNKNOWN
Author-email: UNKNOWN
License: UNKNOWN
Platform: UNKNOWN
